njuseg/__init__.py
njuseg/run.py
njuseg/segmenter.py
njuseg/model/BaseSegmenter.py
njuseg/model/SequenceTagger.py
njuseg/model/__init__.py
njuseg/model/evaluation.py
njuseg/model/init.py
njuseg/model/module.py
njuseg/model/yaml_config.py
njuseg-2.0.dist-info/DESCRIPTION.rst
njuseg-2.0.dist-info/METADATA
njuseg-2.0.dist-info/RECORD
njuseg-2.0.dist-info/WHEEL
njuseg-2.0.dist-info/metadata.json
njuseg-2.0.dist-info/top_level.txt
