Metadata-Version: 2.0
Name: njuseg
Version: 2.0
Summary: Chinese Word Segmenter developed by Nanjing University NLP Group
Home-page: UNKNOWN
Author: Jiahuan Li, Tong Pu, Huiyun Yang, Yu Bao
Author-email: lijh@nlp.nju.edu.cn
License: MIT
Platform: UNKNOWN
Classifier: Programming Language :: Python :: 3
Classifier: Programming Language :: Python :: 3.6
Classifier: Programming Language :: Python :: 3.7
Requires-Dist: torchtext (>=0.3.0)
